st_img_carousel/__init__.py
st_img_carousel/frontend/public/build/bundle.js
st_img_carousel/frontend/public/build/bundle.js.map
st_img_carousel-0.0.5.dist-info/METADATA
st_img_carousel-0.0.5.dist-info/WHEEL
st_img_carousel-0.0.5.dist-info/top_level.txt
st_img_carousel-0.0.5.dist-info/RECORD
