Metadata-Version: 2.1
Name: st-img-carousel
Version: 0.0.5
Summary: Streamlit component that allows to create image carousel
Home-page: 
Author: Ahsanul Haque
Author-email: ahsanul.haque.ovi@gmail.com
Requires-Python: >=3.7
Requires-Dist: streamlit (>=0.63)
Provides-Extra: devel
Requires-Dist: wheel ; extra == 'devel'
Requires-Dist: pytest (==7.4.0) ; extra == 'devel'
Requires-Dist: playwright (==1.36.0) ; extra == 'devel'
Requires-Dist: requests (==2.31.0) ; extra == 'devel'
Requires-Dist: pytest-playwright-snapshot (==1.0) ; extra == 'devel'
Requires-Dist: pytest-rerunfailures (==12.0) ; extra == 'devel'
